climacast/__main__.py
climacast/__setup__.py
climacast/weather.py
climacast/weather_ascii.py
climacast-4.0.6.dist-info/LICENSE
climacast-4.0.6.dist-info/METADATA
climacast-4.0.6.dist-info/WHEEL
climacast-4.0.6.dist-info/entry_points.txt
climacast-4.0.6.dist-info/RECORD
