Metadata-Version: 2.1
Name: climacast
Version: 4.0.6
Summary: A minimal console based weather application.
License: GPL-3.0
Author: Shvetank Dattatreya
Author-email: dshvetank@gmail.com
Requires-Python: >=3.11,<4.0
Classifier: License :: OSI Approved :: GNU General Public License v3 (GPLv3)
Classifier: Programming Language :: Python :: 3
Classifier: Programming Language :: Python :: 3.11
Classifier: Programming Language :: Python :: 3.12
